{
  "rulesDirectory": ["tslint-plugin-prettier"],
  "extends": [
    "tslint:latest",
    "tslint-config-google",
    "tslint-config-prettier"
  ],
  "linterOptions": {
    "exclude": [
      "config/**/*.js",
      "node_modules/**/*.ts",
      "coverage/lcov-report/*.js"
    ]
  },
  "rules": {
    "prettier": [
      true,
      {
        "semi": true,
        "singleQuote": true,
        "printWidth": 120,
        "trailingComma": "all"
      }
    ],
    "no-console": false,
    "no-bitwise": false,
    "variable-name": [
      true,
      "ban-keywords",
      "check-format",
      "allow-pascal-case",
      "allow-leading-underscore"
    ],
    "import-name": false,
    "ordered-imports": false,
    "interface-name": false,
    "no-empty-interface": false,
    "object-literal-sort-keys": false,
    "object-literal-shorthand": false,
    "no-empty": [true, "allow-empty-functions"],
    "no-implicit-dependencies": [true, "dev"],
    "no-submodule-imports": false,
    "no-unused-expression": [true, "allow-fast-null-checks"],
    "no-object-literal-type-assertion": false
},
  "jsRules": {}
}
